main.py
audio/sound.py
entities/bullet.py
entities/enemy.py
entities/player.py
game/__init__.py
game/constants.py
game/loop.py
game/state.py
network/client.py
network/server.py
termoot-0.1.1.dist-info/licenses/LICENSE
ui/dialogs.py
ui/draw.py
ui/lobby.py
world/walls.py
termoot-0.1.1.dist-info/METADATA
termoot-0.1.1.dist-info/WHEEL
termoot-0.1.1.dist-info/entry_points.txt
termoot-0.1.1.dist-info/top_level.txt
termoot-0.1.1.dist-info/RECORD
