Metadata-Version: 2.4
Name: termoot
Version: 0.1.1
Summary: A terminal-based multiplayer shooter game
Author-email: TangoBee <querytango@gmail.com>
License: MIT
Project-URL: Homepage, https://github.com/TangoBeee/termoot
Project-URL: Repository, https://github.com/TangoBeee/termoot
Project-URL: Issues, https://github.com/TangoBeee/termoot/issues
Classifier: Development Status :: 3 - Alpha
Classifier: Intended Audience :: End Users/Desktop
Classifier: Topic :: Games/Entertainment :: Arcade
Classifier: License :: OSI Approved :: MIT License
Classifier: Programming Language :: Python :: 3
Classifier: Programming Language :: Python :: 3.10
Classifier: Programming Language :: Python :: 3.11
Classifier: Programming Language :: Python :: 3.12
Classifier: Programming Language :: Python :: 3.14
Classifier: Environment :: Console :: Curses
Requires-Python: >=3.10
License-File: LICENSE
Requires-Dist: windows-curses; platform_system == "Windows"
Dynamic: license-file
